config/__init__.py
config/api.py
config/configuration.py
config/handlers.py
config/merge_template.json
py_configuration_Orinnass-2.9.6.data/scripts/config_cli.py
py_configuration_Orinnass-2.9.6.dist-info/METADATA
py_configuration_Orinnass-2.9.6.dist-info/WHEEL
py_configuration_Orinnass-2.9.6.dist-info/top_level.txt
py_configuration_Orinnass-2.9.6.dist-info/RECORD
