Metadata-Version: 2.1
Name: py-configuration-Orinnass
Version: 2.9.6
Summary: UNKNOWN
Home-page: UNKNOWN
License: UNKNOWN
Download-URL: https://gitlab.com/Orinnass/python-module-configuration
Platform: UNKNOWN
Requires-Python: >=3.10
Requires-Dist: attrs (>=21.2.0)
Requires-Dist: click (>=8.0.3)
Requires-Dist: colorama (>=0.4.4)
Requires-Dist: Flask (>=2.0.2)
Requires-Dist: itsdangerous (>=2.0.1)
Requires-Dist: Jinja2 (>=3.0.3)
Requires-Dist: jsonschema (>=4.2.1)
Requires-Dist: MarkupSafe (>=2.0.1)
Requires-Dist: py-tools-Orinnass (>=2.0.10)
Requires-Dist: PyMySQL (>=1.0.2)
Requires-Dist: pyrsistent (>=0.18.0)
Requires-Dist: six (>=1.16.0)
Requires-Dist: Werkzeug (>=2.0.2)
